{
  "news_links": [
    {"title": "深学细悟正确政绩观 坚守育人实干初心——商务贸易学院全体党员参加专题党课学习", "url": "https://swmy.hnae.edu.cn/info/1181/8515.htm", "date": "2026-07-02"},
    {"title": "商务贸易学院教工党支部召开预备党员转正大会", "url": "https://swmy.hnae.edu.cn/info/1181/8275.htm", "date": "2026-06-01"},
    {"title": "深学细悟两会精神 勇担教育育人使命 —— 党委委员、副校长周金宗为三院党员讲授专题党课", "url": "https://swmy.hnae.edu.cn/info/1181/8065.htm", "date": "2026-04-17"},
    {"title": "商务贸易学院教工党支部召开2025年度组织生活会暨民主评议党员大会", "url": "https://swmy.hnae.edu.cn/info/1181/7945.htm", "date": "2026-03-22"},
    {"title": "深入学习贯彻党的二十届四中全会精神——校党委委员、副校长周金宗为商务贸易学院全体教师作专题宣讲", "url": "https://swmy.hnae.edu.cn/info/1181/8015.htm", "date": "2025-12-26"},
    {"title": "商务贸易学院教工党支部召开接收预备党员大会", "url": "https://swmy.hnae.edu.cn/info/1181/7725.htm", "date": "2025-11-28"},
    {"title": "商务贸易学院党总支开展11月主题党日活动", "url": "https://swmy.hnae.edu.cn/info/1181/7635.htm", "date": "2025-11-14"},
    {"title": "商务贸易学院党总支部举行2025下期分党校入党积极分子培训开班典礼", "url": "https://swmy.hnae.edu.cn/info/1181/7605.htm", "date": "2025-11-07"},
    {"title": "学深悟透 笃信笃行——商贸学院开展学习《习近平谈治国理政》第五卷座谈会", "url": "https://swmy.hnae.edu.cn/info/1181/7485.htm", "date": "2025-09-29"},
    {"title": "商务贸易学院组织师生收看纪念中国人民抗日战争暨世界反法西斯战争胜利80周年大会", "url": "https://swmy.hnae.edu.cn/info/1181/7385.htm", "date": "2025-09-04"},
    {"title": "商贸学院党总支部组织开展走进图书馆阅读图书教育实践活动", "url": "https://swmy.hnae.edu.cn/info/1181/2625.htm", "date": "2024-03-23"},
    {"title": "《大美中国·春天系列》春天的湖南：让商贸党员师生感悟美丽湖南建设成就", "url": "https://swmy.hnae.edu.cn/info/1181/2615.htm", "date": "2024-02-27"},
    {"title": "商贸学院开展2月份微党课学习活动", "url": "https://swmy.hnae.edu.cn/info/1181/2595.htm", "date": "2024-02-23"},
    {"title": "商贸学院开展1月份微党课学习活动", "url": "https://swmy.hnae.edu.cn/info/1181/2585.htm", "date": "2024-01-26"},
    {"title": "正风不止步 肃纪不停歇——商贸学院党总支组织观看《正风肃纪》警示教育片", "url": "https://swmy.hnae.edu.cn/info/1181/2575.htm", "date": "2024-01-10"},
    {"title": "商务贸易学院党支部开展“寻初心豪情 学使命担当”主题党日活动", "url": "https://swmy.hnae.edu.cn/info/1181/2545.htm", "date": "2023-12-27"},
    {"title": "2023年下半年商贸学院教工党支部接收预备党员大会召开", "url": "https://swmy.hnae.edu.cn/info/1181/2535.htm", "date": "2023-12-08"},
    {"title": "商务贸易学院教工党支部举行2023年预备党员转正大会", "url": "https://swmy.hnae.edu.cn/info/1181/2525.htm", "date": "2023-12-08"},
    {"title": "商贸学院党支部开展《志愿军：雄兵出击》党性锤炼观影活动", "url": "https://swmy.hnae.edu.cn/info/1181/2505.htm", "date": "2023-11-24"},
    {"title": "商贸学院党总支十一月党课开课", "url": "https://swmy.hnae.edu.cn/info/1181/2485.htm", "date": "2023-11-17"},
    {"title": "商贸学院组织党员师生收看第三届“一带一路”国际合作高峰论坛直播", "url": "https://swmy.hnae.edu.cn/info/1181/2465.htm", "date": "2023-10-20"},
    {"title": "商贸学院党总支召开学习贯彻习近平新时代中国特色社会主义思想主题教育专题组织生活会", "url": "https://swmy.hnae.edu.cn/info/1181/2455.htm", "date": "2023-09-16"},
    {"title": "商务贸易学院八月份主题党日活动举行", "url": "https://swmy.hnae.edu.cn/info/1181/3035.htm", "date": "2023-08-18"},
    {"title": "商贸学院开展“党建引领推动垃圾分类成为低碳生活新时尚”主题党日活动", "url": "https://swmy.hnae.edu.cn/info/1181/3025.htm", "date": "2023-07-20"},
    {"title": "商贸学院组织全体党员在线观看系列专题影片《七七事变》", "url": "https://swmy.hnae.edu.cn/info/1181/3015.htm", "date": "2023-07-08"},
    {"title": "商务贸易学院六月份主题党日活动举行", "url": "https://swmy.hnae.edu.cn/info/1181/2995.htm", "date": "2023-06-17"},
    {"title": "党委委员、副院长周金宗为商贸党员师生讲授主题教育专题党课", "url": "https://swmy.hnae.edu.cn/info/1181/2975.htm", "date": "2023-05-18"},
    {"title": "商务贸易学院五月份主题党日活动举行", "url": "https://swmy.hnae.edu.cn/info/1181/2955.htm", "date": "2023-05-06"},
    {"title": "商务贸易学院党总支部开展四月份专题党课学习——学习株洲市优秀共产党员严亮同志的优秀事迹", "url": "https://swmy.hnae.edu.cn/info/1181/2935.htm", "date": "2023-04-08"},
    {"title": "商务贸易学院四月份主题党日活动举行", "url": "https://swmy.hnae.edu.cn/info/1181/2925.htm", "date": "2023-04-08"},
    {"title": "党建引领铸师魂，课堂示范展风采——商务贸易学院三月份主题党日活动举行", "url": "https://swmy.hnae.edu.cn/info/1181/2905.htm", "date": "2023-03-16"},
    {"title": "商务贸易学院教工党支部开展2022年度组织生活会和民主评议党员活动", "url": "https://swmy.hnae.edu.cn/info/1181/2915.htm", "date": "2023-03-16"},
    {"title": "奋进新征程 建功新时代——商务贸易学院党总支部开展二月份专题党课学习主题党日活动", "url": "https://swmy.hnae.edu.cn/info/1181/2895.htm", "date": "2023-02-24"},
    {"title": "商贸学院召开学院第四届教职工代表大会暨工会会员大会代表选举会议", "url": "https://swmy.hnae.edu.cn/info/1181/2885.htm", "date": "2023-02-14"},
    {"title": "奋斗正当时，再上新征程——商务贸易学院党总支二0二三年一月份主题党日活动顺利召开", "url": "https://swmy.hnae.edu.cn/info/1181/2865.htm", "date": "2023-01-16"},
    {"title": "2022年下半年商贸学院教工党支部预备党员转正大会召开", "url": "https://swmy.hnae.edu.cn/info/1181/2855.htm", "date": "2022-12-29"},
    {"title": "商务贸易学院党总支十二月份主题党日活动顺利召开", "url": "https://swmy.hnae.edu.cn/info/1181/2825.htm", "date": "2022-12-24"},
    {"title": "2022年下半年商贸学院教工党支部接收预备党员大会召开", "url": "https://swmy.hnae.edu.cn/info/1181/2815.htm", "date": "2022-12-09"},
    {"title": "\"疫\"线主题党日，让党旗在疫情防控一线高高飘扬——商务贸易学院党总支十一月主题党日活动召开", "url": "https://swmy.hnae.edu.cn/info/1181/2795.htm", "date": "2022-11-30"},
    {"title": "学习二十大 凝聚青年心——商务贸易学院组织学习二十大原文活动", "url": "https://swmy.hnae.edu.cn/info/1181/2785.htm", "date": "2022-11-29"},
    {"title": "踔厉奋发担使命，勇毅前行向未来——商务贸易学院党总支十月份主题党日活动顺利召开", "url": "https://swmy.hnae.edu.cn/info/1181/2755.htm", "date": "2022-10-29"},
    {"title": "无愧今天的使命担当，不负明天的伟大梦想", "url": "https://swmy.hnae.edu.cn/info/1181/3085.htm", "date": "2022-10-17"},
    {"title": "商务贸易学院2022级新生入党启蒙教育顺利开展", "url": "https://swmy.hnae.edu.cn/info/1181/3075.htm", "date": "2022-09-30"},
    {"title": "商务贸易学院党总支部召开总支委员补选大会", "url": "https://swmy.hnae.edu.cn/info/1181/3445.htm", "date": "2022-09-24"},
    {"title": "传承红色基因 凝聚奋进力量——商务贸易学院党总支九月份主题党日活动召开", "url": "https://swmy.hnae.edu.cn/info/1181/3055.htm", "date": "2022-09-24"},
    {"title": "商务贸易学院党总支（筹）组织全院师生收看《为时代育新人》第二集 《远方——在复兴的赛道上》", "url": "https://swmy.hnae.edu.cn/info/1181/3435.htm", "date": "2022-07-15"},
    {"title": "商务贸易学院（筹）党总支召开出席学校第二次党代会代表选举大会", "url": "https://swmy.hnae.edu.cn/info/1181/3365.htm", "date": "2022-07-08"},
    {"title": "商务贸易学院（筹）党总支七月份主题党日活动召开", "url": "https://swmy.hnae.edu.cn/info/1181/3415.htm", "date": "2022-07-08"},
    {"title": "商务贸易学院党总支六月份主题党日活动召开", "url": "https://swmy.hnae.edu.cn/info/1181/3355.htm", "date": "2022-06-26"},
    {"title": "商务贸易学院党总支开展关于深化整治领导干部违规收送红包礼金专题组织生活会", "url": "https://swmy.hnae.edu.cn/info/1181/3305.htm", "date": "2022-06-05"},
    {"title": "商务贸易学院党总支五月份主题党日活动召开", "url": "https://swmy.hnae.edu.cn/info/1181/3285.htm", "date": "2022-05-25"},
    {"title": "2022年上半年商贸学院教工党支部预备党员转正大会召开", "url": "https://swmy.hnae.edu.cn/info/1181/3275.htm", "date": "2022-05-09"},
    {"title": "商务贸易学院党总支四月份主题党日活动召开", "url": "https://swmy.hnae.edu.cn/info/1181/3265.htm", "date": "2022-04-29"},
    {"title": "商务贸易学院党总支三月份主题党日活动召开", "url": "https://swmy.hnae.edu.cn/info/1181/3245.htm", "date": "2022-03-28"},
    {"title": "商务贸易学院教工支部2021年度组织生活会暨民主评议党员大会顺利召开", "url": "https://swmy.hnae.edu.cn/info/1181/3235.htm", "date": "2022-03-25"},
    {"title": "商务贸易学院（筹）党总支召开1月份主题党日活动", "url": "https://swmy.hnae.edu.cn/info/1181/3215.htm", "date": "2022-01-18"},
    {"title": "商贸学院教工党支部召开新党员发展大会", "url": "https://swmy.hnae.edu.cn/info/1181/3195.htm", "date": "2021-12-30"},
    {"title": "商务贸易学院（筹）党总支召开十二月份主题党日活动", "url": "https://swmy.hnae.edu.cn/info/1181/3185.htm", "date": "2021-12-30"},
    {"title": "商务贸易学院党总支组织11月份主题党日活动", "url": "https://swmy.hnae.edu.cn/info/1181/3155.htm", "date": "2021-11-27"},
    {"title": "商务贸易学院（筹）党总支十月份主题党日活动顺利开展", "url": "https://swmy.hnae.edu.cn/info/1181/3135.htm", "date": "2021-11-01"},
    {"title": "商务贸易学院开展 2021 级新生入党启蒙教育", "url": "https://swmy.hnae.edu.cn/info/1181/3115.htm", "date": "2021-10-26"}
  ]
}